compare_with_remote
