Metadata-Version: 1.1
Name: compare-with-remote
Version: 0.12.0
Summary:  Compare local script output with remote script output
Home-page: https://github.com/guettli/compare-with-remote/
Author: Thomas Guettler
Author-email: info.compare-with-remote@thomas-guettler.de
License: Apache Software License 2.0
Platform: UNKNOWN
Classifier: Development Status :: 3 - Alpha
Classifier: Intended Audience :: Developers
Classifier: License :: OSI Approved :: Apache Software License
Classifier: Programming Language :: Python :: 2
Classifier: Programming Language :: Python :: 2.7
Classifier: Programming Language :: Python :: 3
Classifier: Programming Language :: Python :: 3.5
